src/__init__.py
src/argparser.py
src/cmManager.py
src/fileSystemUtils.py
src/logfileUtils.py
src/main.py
Commit_Man-0.0.3.dist-info/LICENSE
Commit_Man-0.0.3.dist-info/METADATA
Commit_Man-0.0.3.dist-info/WHEEL
Commit_Man-0.0.3.dist-info/entry_points.txt
Commit_Man-0.0.3.dist-info/top_level.txt
Commit_Man-0.0.3.dist-info/RECORD
