Metadata-Version: 2.1
Name: Commit-Man
Version: 0.0.3
Summary: Official Commit man python package
Home-page: https://github.com/atharva-Gundawar/commit-man
Author: Atharva Gundawar
Author-email: atharva.n.gundawar@gmail.com
License: MIT
Keywords: git commit version-control-system vcs
Platform: UNKNOWN
Classifier: License :: OSI Approved :: MIT License
Classifier: Programming Language :: Python
Classifier: Programming Language :: Python :: 3
Classifier: Programming Language :: Python :: 3.6
Classifier: Programming Language :: Python :: Implementation :: CPython
Classifier: Programming Language :: Python :: Implementation :: PyPy
Classifier: Operating System :: OS Independent
Requires-Python: >=3.6.0
Requires-Dist: datetime
Requires-Dist: gitignore-parser
Requires-Dist: docopt
